LICENSE
README.md
pyproject.toml
setup.py
pysavedata/__init__.py
pysavedata/data_controller.py
pysavedata/data_reader.py
pysavedata.egg-info/PKG-INFO
pysavedata.egg-info/SOURCES.txt
pysavedata.egg-info/dependency_links.txt
pysavedata.egg-info/top_level.txt
tests/test_1.py