Metadata-Version: 2.1
Name: pysavedata
Version: 0.0.1
Summary: Python module for convenient storage of classes in files.
Home-page: https://github.com/GigantPro/pysavedata
Download-URL: https://github.com/Peopl3s/club-house-api/archive/main.zip
Author: GigantPro
Author-email: gigantpro2000@gmail.ru
License: The GPLv3 License (GPLv3), see LICENSE file
Classifier: Operating System :: OS Independent
Classifier: Intended Audience :: End Users/Desktop
Classifier: Intended Audience :: Developers
Classifier: Programming Language :: Python
Classifier: Programming Language :: Python :: 3.10
Classifier: Programming Language :: Python :: Implementation :: PyPy
License-File: LICENSE
